mongodb_mcp_bridge/__init__.py
mongodb_mcp_bridge-0.1.0.dist-info/METADATA
mongodb_mcp_bridge-0.1.0.dist-info/WHEEL
mongodb_mcp_bridge-0.1.0.dist-info/entry_points.txt
mongodb_mcp_bridge-0.1.0.dist-info/licenses/LICENSE
mongodb_mcp_bridge-0.1.0.dist-info/RECORD
