Metadata-Version: 2.4
Name: mongodb-mcp-bridge
Version: 0.1.0
Summary: MCP server implementation for MongoDB integration
Author: Syed Asad
License-Expression: MIT
License-File: LICENSE
Requires-Python: >=3.12
Requires-Dist: mcp>=0.1.0
Requires-Dist: motor>=3.3.2
Requires-Dist: pydantic>=2.6.0
Requires-Dist: pymongo>=4.6.0
Requires-Dist: python-dotenv>=1.0.0
Requires-Dist: typing-extensions>=4.9.0
